m3d/__init__.py
m3d/base.py
m3d/common.py
m3d/dual_quaternion.py
m3d/orientation.py
m3d/py.typed
m3d/quaternion.py
m3d/transform.py
m3d/vector.py
m3d-1.1.1.dist-info/WHEEL
m3d-1.1.1.dist-info/METADATA
m3d-1.1.1.dist-info/RECORD
