Metadata-Version: 2.3
Name: m3d
Version: 1.1.1
Summary: Python3 3D transformation library with object oriented API and MIT licensed
Author: Kurant Robotics
Author-email: Kurant Robotics <olivier.roulet@solwr.com>
License: MIT
Classifier: Programming Language :: Python
Classifier: Programming Language :: Python :: 3.10
Classifier: Programming Language :: Python :: 3.11
Classifier: Programming Language :: Python :: 3.12
Classifier: Programming Language :: Python :: 3.13
Classifier: Development Status :: 5 - Production/Stable
Classifier: Intended Audience :: Developers
Classifier: Operating System :: OS Independent
Classifier: Topic :: Software Development :: Libraries :: Python Modules
Requires-Dist: numpy
Requires-Dist: scipy ; extra == 'orientation-mean'
Requires-Python: >=3.10
Project-URL: Homepage, https://gitlab.com/kurant-open/m3d
Provides-Extra: orientation-mean
